ringcentral_bot_framework_extension_botinfo/__init__.py
ringcentral_bot_framework_extension_world_time/__init__.py
ringcentral_bot_framework_extension_world_time-0.2.0.dist-info/LICENSE
ringcentral_bot_framework_extension_world_time-0.2.0.dist-info/METADATA
ringcentral_bot_framework_extension_world_time-0.2.0.dist-info/WHEEL
ringcentral_bot_framework_extension_world_time-0.2.0.dist-info/top_level.txt
ringcentral_bot_framework_extension_world_time-0.2.0.dist-info/RECORD
